listcolouring/__init__.py
listcolouring-0.2.0.dist-info/LICENSE
listcolouring-0.2.0.dist-info/METADATA
listcolouring-0.2.0.dist-info/WHEEL
listcolouring-0.2.0.dist-info/RECORD
